Mips monociclo/src/alu.v
module alu (
    input [31:0] input1,
    input [31:0] input2,
    input [3:0] alu_control,
    output reg [31:0] result,
    output zero
);
    // Sinal de comparação para instruções tipo beq
    assign zero = (result === 32'b0);

    always @(*) begin
        case (alu_control)
            4'b0010: result = input1 + input2;                  // ADD, ADDI
            4'b0110: result = input1 - input2;                  // SUB
            4'b0000: result = input1 & input2;                  // AND
            4'b0001: result = input1 | input2;                  // OR
            4'b0111: result = (input1 < input2) ? 32'b1 : 32'b0; // SLT
            default: result = 32'b0;
        endcase
    end
endmodule

Mips monociclo/src/alu_control.v
module alu_control (
    input [1:0] alu_op,
    input [5:0] funct,
    output reg [3:0] alu_control
);
    always @(*) begin
        case (alu_op)
            2'b00: alu_control = 4'b0010; // lw/sw -> ADD
            2'b01: alu_control = 4'b0110; // beq   -> SUB
            2'b10: begin                  // R-type
                case (funct)
                    6'b100000: alu_control = 4'b0010; // ADD
                    6'b100010: alu_control = 4'b0110; // SUB
                    6'b100100: alu_control = 4'b0000; // AND
                    6'b100101: alu_control = 4'b0001; // OR
                    6'b101010: alu_control = 4'b0111; // SLT
                    default:   alu_control = 4'b0000;
                endcase
            end
            default: alu_control = 4'b0000;
        endcase
    end
endmodule

Mips monociclo/src/reg_file.v
module reg_file (
    input clk,
    input reg_write,
    input [4:0] read_reg1,
    input [4:0] read_reg2,
    input [4:0] write_reg,
    input [31:0] write_data,
    output [31:0] read_data1,
    output [31:0] read_data2
);
    reg [31:0] registers [0:31]; // 32 registradores de 32 bits
    wire [31:0] reg_t2;
    assign reg_t2 = registers[10];

    // Leitura assíncrona
    assign read_data1 = registers[read_reg1];
    assign read_data2 = registers[read_reg2];

    // Escrita síncrona
    always @(posedge clk) begin
        if (reg_write && write_reg != 0) begin
            registers[write_reg] <= write_data;
            $display("[$time] registrador[%0d] <= %d", write_reg, write_data);
        end
        registers[0] <= 0; // <- Garante que $zero nunca muda e sempre retorna 0

    end

endmodule

Mips monociclo/src/instr_mem.v
module instr_mem(input [31:0] addr, output [31:0] instr);
    reg [31:0] memory [0:63]; // ROM com 64 palavras de 32 bits

    initial begin
        memory[0] = 32'h20080005; // addi $t0, $zero, 5
        memory[1] = 32'h2009000A; // addi $t1, $zero, 10
        memory[2] = 32'h01095020; // add  $t2, $t0, $t1
        memory[3] = 32'h00000000; // NOP
        memory[4] = 32'h00000000; // NOP
        memory[5] = 32'h00000000; // NOP
        memory[6] = 32'h00000000; // NOP
        memory[7] = 32'h00000000; // NOP
    end

    assign instr = (addr[31:2] < 64) ? memory[addr[31:2]] : 32'h00000000;
endmodule

Mips monociclo/src/pc.v
module pc(input clk, input reset, input [31:0] pc_in, output reg [31:0] pc_out);
    always @(posedge clk or posedge reset) begin
        if (reset)
            pc_out <= 0;
        else
            pc_out <= pc_in;
    end
endmodule

Mips monociclo/src/cpu.v
module cpu(input clk, input reset);
    // PC wires
    wire [31:0] pc_out, pc_in;

    // Instrução
    wire [31:0] instr;

    // Campos da instrução
    wire [5:0] opcode, funct;
    wire [4:0] rs, rt, rd;
    wire [15:0] imm;
    wire [31:0] sign_ext_imm;

    // Registradores
    wire [31:0] read_data1, read_data2;
    wire [31:0] alu_src2;
    wire [31:0] alu_result;

    // Controle
    wire reg_write;
    wire [3:0] alu_control;
    wire alu_src;
    wire reg_dst;
    wire [1:0] alu_op;  // NOVO sinal de entrada para alu_control

    assign opcode = instr[31:26];
    assign rs     = instr[25:21];
    assign rt     = instr[20:16];
    assign rd     = instr[15:11];
    assign imm    = instr[15:0];
    assign funct  = instr[5:0];

    assign sign_ext_imm = {{16{imm[15]}}, imm};

    assign alu_src = (opcode != 6'b000000);              // I-type usa imediato
    assign reg_dst = (opcode == 6'b000000);              // R-type escreve em rd
    assign reg_write = 1'b1;                             // ainda fixo
    assign alu_op = (opcode == 6'b000000) ? 2'b10 :      // R-type
                    (opcode == 6'b000100) ? 2'b01 :      // beq
                    2'b00;                               // lw/sw/addi/etc.

    assign alu_src2 = alu_src ? sign_ext_imm : read_data2;
    wire [4:0] write_reg = reg_dst ? rd : rt;

    // PC
    pc pc0 (.clk(clk), .reset(reset), .pc_in(pc_in), .pc_out(pc_out));
    assign pc_in = pc_out + 4;

    // Memória de Instruções
    instr_mem imem (.addr(pc_out), .instr(instr));

    // Banco de Registradores
    reg_file regs (
        .clk(clk),
        .reg_write(reg_write),
        .read_reg1(rs),
        .read_reg2(rt),
        .write_reg(write_reg),
        .write_data(alu_result),
        .read_data1(read_data1),
        .read_data2(read_data2)
    );

    // ALU Control
    alu_control alu_ctrl (
        .alu_op(alu_op),
        .funct(funct),
        .alu_control(alu_control)
    );

    // ALU
    alu alu0 (
        .input1(read_data1),
        .input2(alu_src2),
        .alu_control(alu_control),
        .result(alu_result),
        .zero()
    );
endmodule

Mips monociclo/tb/tb_cpu.v
`timescale 1ns/1ps
module tb_cpu;
    reg clk = 0;
    reg reset;

    cpu uut (.clk(clk), .reset(reset));

    always #5 clk = ~clk;

    initial begin
        $dumpfile("sim/dump_cpu.vcd");
        $dumpvars(0, tb_cpu);

        reset = 1; #10;
        reset = 0;

        #100; // Roda alguns ciclos
        $finish;
    end
endmodule

Mips monociclo/sim/dump_cpu.vcd
$date
	Wed Apr 02 20:38:50 2025
$end
$version
	Icarus Verilog
$end
$timescale
	1ps
$end
$scope module tb_cpu $end
$var reg 1 ! clk $end
$var reg 1 " reset $end
$scope module uut $end
$var wire 1 ! clk $end
$var wire 1 # reg_write $end
$var wire 1 " reset $end
$var wire 5 $ write_reg [4:0] $end
$var wire 32 % sign_ext_imm [31:0] $end
$var wire 5 & rt [4:0] $end
$var wire 5 ' rs [4:0] $end
$var wire 1 ( reg_dst $end
$var wire 32 ) read_data2 [31:0] $end
$var wire 32 * read_data1 [31:0] $end
$var wire 5 + rd [4:0] $end
$var wire 32 , pc_out [31:0] $end
$var wire 32 - pc_in [31:0] $end
$var wire 6 . opcode [5:0] $end
$var wire 32 / instr [31:0] $end
$var wire 16 0 imm [15:0] $end
$var wire 6 1 funct [5:0] $end
$var wire 32 2 alu_src2 [31:0] $end
$var wire 1 3 alu_src $end
$var wire 32 4 alu_result [31:0] $end
$var wire 2 5 alu_op [1:0] $end
$var wire 4 6 alu_control [3:0] $end
$scope module alu0 $end
$var wire 32 7 input2 [31:0] $end
$var wire 1 8 zero $end
$var wire 32 9 input1 [31:0] $end
$var wire 4 : alu_control [3:0] $end
$var reg 32 ; result [31:0] $end
$upscope $end
$scope module alu_ctrl $end
$var wire 2 < alu_op [1:0] $end
$var wire 6 = funct [5:0] $end
$var reg 4 > alu_control [3:0] $end
$upscope $end
$scope module imem $end
$var wire 32 ? instr [31:0] $end
$var wire 32 @ addr [31:0] $end
$upscope $end
$scope module pc0 $end
$var wire 1 ! clk $end
$var wire 32 A pc_in [31:0] $end
$var wire 1 " reset $end
$var reg 32 B pc_out [31:0] $end
$upscope $end
$scope module regs $end
$var wire 1 ! clk $end
$var wire 32 C read_data1 [31:0] $end
$var wire 32 D read_data2 [31:0] $end
$var wire 5 E read_reg1 [4:0] $end
$var wire 5 F read_reg2 [4:0] $end
$var wire 32 G reg_t2 [31:0] $end
$var wire 1 # reg_write $end
$var wire 32 H write_data [31:0] $end
$var wire 5 I write_reg [4:0] $end
$upscope $end
$upscope $end
$upscope $end
$enddefinitions $end
$comment Show the parameter values. $end
$dumpall
$end
#0
$dumpvars
b1000 I
bx H
bx G
b1000 F
b0 E
bx D
bx C
b0 B
b100 A
b0 @
b100000000010000000000000000101 ?
b10 >
b101 =
b0 <
bx ;
b10 :
bx 9
08
b101 7
b10 6
b0 5
bx 4
13
b101 2
b101 1
b101 0
b100000000010000000000000000101 /
b1000 .
b100 -
b0 ,
b0 +
bx *
bx )
0(
b0 '
b1000 &
b101 %
b1000 $
1#
1"
0!
$end
#5000
b101 4
b101 ;
b101 H
b0 *
b0 9
b0 C
1!
#10000
0!
0"
#15000
b1010 4
b1010 ;
b1010 H
b1010 2
b1010 7
b1001 $
b1001 I
b1010 1
b1010 =
b1010 %
b1010 0
b1001 &
b1001 F
b100000000010010000000000001010 /
b100000000010010000000000001010 ?
b1000 -
b1000 A
b100 ,
b100 @
b100 B
bx )
bx D
1!
#20000
0!
#25000
b1111 4
b1111 ;
b1111 H
b1010 $
b1010 I
b10 5
b10 <
b100000 1
b100000 =
b101000000100000 %
b101000000100000 0
b1010 +
b101 *
b101 9
b101 C
b1000 '
b1000 E
03
1(
b0 .
b1000010010101000000100000 /
b1000010010101000000100000 ?
b1100 -
b1100 A
b1000 ,
b1000 @
b1000 B
b1010 )
b1010 D
1!
#30000
0!
#35000
18
b0 6
b0 :
b0 >
b0 $
b0 I
b0 2
b0 7
b0 4
b0 ;
b0 H
b0 1
b0 =
b0 %
b0 0
b0 +
b0 )
b0 D
b0 &
b0 F
b0 *
b0 9
b0 C
b0 '
b0 E
b0 /
b0 ?
b10000 -
b10000 A
b1100 ,
b1100 @
b1100 B
b1111 G
1!
#40000
0!
#45000
b10100 -
b10100 A
b10000 ,
b10000 @
b10000 B
1!
#50000
0!
#55000
b11000 -
b11000 A
b10100 ,
b10100 @
b10100 B
1!
#60000
0!
#65000
b11100 -
b11100 A
b11000 ,
b11000 @
b11000 B
1!
#70000
0!
#75000
b100000 -
b100000 A
b11100 ,
b11100 @
b11100 B
1!
#80000
0!
#85000
08
bx 4
bx ;
bx H
bx 2
bx 7
bx $
bx I
bx 5
bx <
bx 1
bx =
bx %
bx 0
bx +
bx )
bx D
bx &
bx F
bx *
bx 9
bx C
bx '
bx E
x3
x(
bx .
bx /
bx ?
b100100 -
b100100 A
b100000 ,
b100000 @
b100000 B
1!
#90000
0!
#95000
b101000 -
b101000 A
b100100 ,
b100100 @
b100100 B
1!
#100000
0!
#105000
b101100 -
b101100 A
b101000 ,
b101000 @
b101000 B
1!
