Mips monociclo/src/data_men.v
module data_mem (
    input clk,
    input mem_read,
    input mem_write,
    input [31:0] addr,
    input [31:0] write_data,
    output reg [31:0] read_data
);
    reg [31:0] memory [0:63]; // Memória com 64 palavras de 32 bits

    // Inicializa a memória com valores padrão (opcional)
    initial begin
        integer i;
        for (i = 0; i < 64; i = i + 1) begin
            memory[i] = 32'b0;
        end
    end

    // Leitura assíncrona
    always @(*) begin
        if (mem_read) begin
            read_data = memory[addr[31:2]]; // Alinha o endereço à palavra
        end else begin
            read_data = 32'b0;
        end
    end

    // Escrita síncrona
    always @(posedge clk) begin
        if (mem_write) begin
            memory[addr[31:2]] <= write_data; // Alinha o endereço à palavra
        end
    end
endmodule

Mips monociclo/src/alu.v
module alu (
    input [31:0] input1,
    input [31:0] input2,
    input [3:0] alu_control,

    output reg [31:0] result,
    output zero
);

    always @(*) begin
        case (alu_control)
            4'b0010: result = input1 + input2;                  // ADD, ADDI
            4'b0110: result = input1 - input2;                  // SUB
            4'b0000: result = input1 & input2;                  // AND
            4'b0001: result = input1 | input2;                  // OR
            4'b0111: result = (input1 < input2) ? 1 : 0;        //SLT
            4'b1010:
            begin
                if(input2!=0)result = input1 / input2;          //DIV
                else alu_result = 32'b11111111111111111111111111111111;
            end
            default: result = 0;
        endcase
    end
    assign zero = (result==0);
endmodule

Mips monociclo/src/alu_control.v
module alu_control (
    input [1:0] alu_op,
    input [5:0] funct,
    output reg [3:0] alu_control
);
    always @(*) begin
        case (alu_op)
            2'b00: alu_control = 4'b0010; // lw/sw -> ADD
            2'b01: alu_control = 4'b0110; // beq   -> SUB
            2'b10: begin                  // R-type
                case (funct)
                    6'b100000: alu_control = 4'b0010; // ADD
                    6'b100010: alu_control = 4'b0110; // SUB
                    6'b100100: alu_control = 4'b0000; // AND
                    6'b100101: alu_control = 4'b0001; // OR
                    6'b101010: alu_control = 4'b0111; // SLT
                    default:   alu_control = 4'b0000;
                endcase
            end
            default: alu_control = 4'b0000;
        endcase
    end
endmodule

Mips monociclo/src/control.v
module control (
    input [5:0] opcode,
    output reg reg_dst,
    output reg alu_src,
    output reg mem_to_reg,
    output reg reg_write,
    output reg mem_read,
    output reg mem_write,
    output reg branch,
    output reg jump,
    output reg [1:0] alu_op
);

always @(*) begin
    case (opcode)
        6'b000000: begin // R-type
            reg_dst = 1;
            alu_src = 0;
            mem_to_reg = 0;
            reg_write = 1;
            mem_read = 0;
            mem_write = 0;
            branch = 0;
            jump = 0;
            alu_op = 2'b10;
        end
        6'b100011: begin // LW
            reg_dst = 0;
            alu_src = 1;
            mem_to_reg = 1;
            reg_write = 1;
            mem_read = 1;
            mem_write = 0;
            branch = 0;
            jump = 0;
            alu_op = 2'b00;
        end
        6'b101011: begin // SW
            reg_dst = 0; // Don't care
            alu_src = 1;
            mem_to_reg = 0; // Don't care
            reg_write = 0;
            mem_read = 0;
            mem_write = 1;
            branch = 0;
            jump = 0;
            alu_op = 2'b00;
        end
        6'b000100: begin // BEQ
            reg_dst = 0; // Don't care
            alu_src = 0;
            mem_to_reg = 0; // Don't care
            reg_write = 0;
            mem_read = 0;
            mem_write = 0;
            branch = 1;
            jump = 0;
            alu_op = 2'b01;
        end
        6'b000010: begin // JUMP
            reg_dst = 0; // Don't care
            alu_src = 0; // Don't care
            mem_to_reg = 0; // Don't care
            reg_write = 0;
            mem_read = 0;
            mem_write = 0;
            branch = 0;
            jump = 1;
            alu_op = 2'b00; // Don't care
        end
        default: begin // Default case
            reg_dst = 0;
            alu_src = 0;
            mem_to_reg = 0;
            reg_write = 0;
            mem_read = 0;
            mem_write = 0;
            branch = 0;
            jump = 0;
            alu_op = 2'b00;
        end
    endcase
end

endmodule

Mips monociclo/src/reg_file.v
module reg_file (
    input clk,
    input reg_write,
    input [4:0] read_reg1,
    input [4:0] read_reg2,
    input [4:0] write_reg,
    input [31:0] write_data,
    output [31:0] read_data1,
    output [31:0] read_data2
);
    reg [31:0] registers [0:31]; // 32 registradores de 32 bits
    wire [31:0] reg_t2;
    assign reg_t2 = registers[10];

    // Leitura assíncrona
    assign read_data1 = registers[read_reg1];
    assign read_data2 = registers[read_reg2];

    // Escrita síncrona
    always @(posedge clk) begin
        if (reg_write && write_reg != 0) begin
            registers[write_reg] <= write_data;
            $display("[$time] registrador[%0d] <= %d", write_reg, write_data);
        end
        registers[0] <= 0; // <- Garante que $zero nunca muda e sempre retorna 0

    end

endmodule

Mips monociclo/src/instr_mem.v
module instr_mem(input [31:0] addr, output [31:0] instr);
    reg [31:0] memory [0:63]; // ROM com 64 palavras de 32 bits

    initial begin
        memory[0] = 32'h20080005; // addi $t0, $zero, 5
        memory[1] = 32'h2009000A; // addi $t1, $zero, 10
        memory[2] = 32'h01095020; // add  $t2, $t0, $t1
        memory[3] = 32'h00000000; // NOP
        memory[4] = 32'h00000000; // NOP
        memory[5] = 32'h00000000; // NOP
        memory[6] = 32'h00000000; // NOP
        memory[7] = 32'h00000000; // NOP
    end

    assign instr = (addr[31:2] < 64) ? memory[addr[31:2]] : 32'h00000000;
endmodule

Mips monociclo/src/pc.v
module pc(input clk, input reset, input [31:0] pc_in, output reg [31:0] pc_out);
    always @(posedge clk or posedge reset) begin
        if (reset)
            pc_out <= 0;
        else
            pc_out <= pc_in;
    end
endmodule

Mips monociclo/src/cpu.v
module cpu(input clk, input reset);
    // PC wires
    wire [31:0] pc_out, pc_in;

    // Instrução
    wire [31:0] instr;

    // Campos da instrução
    wire [5:0] opcode, funct;
    wire [4:0] rs, rt, rd;
    wire [15:0] imm;
    wire [31:0] sign_ext_imm;

    // Registradores
    wire [31:0] read_data1, read_data2;
    wire [31:0] alu_src2;
    wire [31:0] alu_result;

    // Sinais de controle
    wire reg_dst, alu_src, mem_to_reg, reg_write;
    wire mem_read, mem_write, branch, jump;
    wire [1:0] alu_op;
    wire [3:0] alu_control;
    wire [31:0] mem_data;
    wire [31:0] write_data;
    wire zero;

    // Decodificação da instrução
    assign opcode = instr[31:26];
    assign rs     = instr[25:21];
    assign rt     = instr[20:16];
    assign rd     = instr[15:11];
    assign imm    = instr[15:0];
    assign funct  = instr[5:0];
    assign sign_ext_imm = {{16{imm[15]}}, imm};

    // Seleção de registrador destino e da segunda entrada da ALU
    wire [4:0] write_reg = reg_dst ? rd : rt;
    assign alu_src2 = alu_src ? sign_ext_imm : read_data2;

    // PC
    pc pc0 (.clk(clk), .reset(reset), .pc_in(pc_in), .pc_out(pc_out));

    // Cálculo do endereço de branch e jump
    wire [31:0] branch_addr = pc_out + 4 + (sign_ext_imm << 2);
    wire branch_taken = branch & zero;
    wire [31:0] jump_addr = {pc_out[31:28], instr[25:0], 2'b00};

    // Próximo valor do PC
    assign pc_in = jump ? jump_addr : (branch_taken ? branch_addr : (pc_out + 4));

    // Memória de instruções
    instr_mem imem (.addr(pc_out), .instr(instr));

    // Banco de registradores
    reg_file regs (
        .clk(clk),
        .reg_write(reg_write),
        .read_reg1(rs),
        .read_reg2(rt),
        .write_reg(write_reg),
        .write_data(write_data),
        .read_data1(read_data1),
        .read_data2(read_data2)
    );

    // Unidade de controle principal
    control control_unit (
        .opcode(opcode),
        .reg_dst(reg_dst),
        .alu_src(alu_src),
        .mem_to_reg(mem_to_reg),
        .reg_write(reg_write),
        .mem_read(mem_read),
        .mem_write(mem_write),
        .branch(branch),
        .jump(jump),
        .alu_op(alu_op)
    );

    // ALU Control
    alu_control alu_ctrl (
        .alu_op(alu_op),
        .funct(funct),
        .alu_control(alu_control)
    );

    // ALU
    alu alu0 (
        .input1(read_data1),
        .input2(alu_src2),
        .alu_control(alu_control),
        .result(alu_result),
        .zero(zero)
    );

    // Memória de dados
    data_mem dmem (
        .clk(clk),
        .mem_read(mem_read),
        .mem_write(mem_write),
        .addr(alu_result),
        .write_data(read_data2),
        .read_data(mem_data)
    );

    // Mux final de escrita no registrador
    assign write_data = mem_to_reg ? mem_data : alu_result;

endmodule

Mips monociclo/tb/tb_cpu.v
`timescale 1ns/1ps
module tb_cpu;
    reg clk = 0;
    reg reset;

    // Instância da CPU
    cpu uut (.clk(clk), .reset(reset));

    // Clock com período de 10ns
    always #5 clk = ~clk;

    initial begin
        $dumpfile("sim/dump_cpu.vcd");
        $dumpvars(0, tb_cpu);

        // Reset inicial
        reset = 1;
        #10;
        reset = 0;

        // Espera a execução de todas as instruções (~8 instruções × 10ns/ciclo)
        #100;

        $display("\n====== VERIFICAÇÃO DOS REGISTRADORES E MEMÓRIA ======");

        $display("$t0 = %d (esperado 5)",  uut.regs.registers[8]);
        $display("$t1 = %d (esperado 10)", uut.regs.registers[9]);
        $display("$t2 = %d (esperado 5)",  uut.regs.registers[10]);
        $display("$t3 = %d (esperado 1)",  uut.regs.registers[11]);
        $display("$t4 = %d (esperado 20)", uut.regs.registers[12]);
        $display("$t5 = %d (esperado 5)",  uut.regs.registers[13]);
        $display("Mem[0] = %d (esperado 5)", uut.dmem.memory[0]);

        $finish;
    end
endmodule

Mips monociclo/sim/dump_cpu.vcd
$date
	Wed Apr 09 14:38:58 2025
$end
$version
	Icarus Verilog
$end
$timescale
	1ps
$end
$scope module tb_cpu $end
$var reg 1 ! clk $end
$var reg 1 " reset $end
$scope module uut $end
$var wire 1 # branch_taken $end
$var wire 1 ! clk $end
$var wire 1 " reset $end
$var wire 1 $ zero $end
$var wire 5 % write_reg [4:0] $end
$var wire 32 & write_data [31:0] $end
$var wire 32 ' sign_ext_imm [31:0] $end
$var wire 5 ( rt [4:0] $end
$var wire 5 ) rs [4:0] $end
$var wire 1 * reg_write $end
$var wire 1 + reg_dst $end
$var wire 32 , read_data2 [31:0] $end
$var wire 32 - read_data1 [31:0] $end
$var wire 5 . rd [4:0] $end
$var wire 32 / pc_out [31:0] $end
$var wire 32 0 pc_in [31:0] $end
$var wire 6 1 opcode [5:0] $end
$var wire 1 2 mem_write $end
$var wire 1 3 mem_to_reg $end
$var wire 1 4 mem_read $end
$var wire 32 5 mem_data [31:0] $end
$var wire 32 6 jump_addr [31:0] $end
$var wire 1 7 jump $end
$var wire 32 8 instr [31:0] $end
$var wire 16 9 imm [15:0] $end
$var wire 6 : funct [5:0] $end
$var wire 32 ; branch_addr [31:0] $end
$var wire 1 < branch $end
$var wire 32 = alu_src2 [31:0] $end
$var wire 1 > alu_src $end
$var wire 32 ? alu_result [31:0] $end
$var wire 2 @ alu_op [1:0] $end
$var wire 4 A alu_control [3:0] $end
$scope module alu0 $end
$var wire 32 B input2 [31:0] $end
$var wire 1 $ zero $end
$var wire 32 C input1 [31:0] $end
$var wire 4 D alu_control [3:0] $end
$var reg 32 E result [31:0] $end
$upscope $end
$scope module alu_ctrl $end
$var wire 6 F funct [5:0] $end
$var wire 2 G alu_op [1:0] $end
$var reg 4 H alu_control [3:0] $end
$upscope $end
$scope module control_unit $end
$var wire 6 I opcode [5:0] $end
$var reg 2 J alu_op [1:0] $end
$var reg 1 > alu_src $end
$var reg 1 < branch $end
$var reg 1 7 jump $end
$var reg 1 4 mem_read $end
$var reg 1 3 mem_to_reg $end
$var reg 1 2 mem_write $end
$var reg 1 + reg_dst $end
$var reg 1 * reg_write $end
$upscope $end
$scope module dmem $end
$var wire 32 K addr [31:0] $end
$var wire 1 ! clk $end
$var wire 1 4 mem_read $end
$var wire 1 2 mem_write $end
$var wire 32 L write_data [31:0] $end
$var reg 32 M read_data [31:0] $end
$scope begin $unm_blk_12 $end
$var integer 32 N i [31:0] $end
$upscope $end
$upscope $end
$scope module imem $end
$var wire 32 O instr [31:0] $end
$var wire 32 P addr [31:0] $end
$upscope $end
$scope module pc0 $end
$var wire 1 ! clk $end
$var wire 32 Q pc_in [31:0] $end
$var wire 1 " reset $end
$var reg 32 R pc_out [31:0] $end
$upscope $end
$scope module regs $end
$var wire 1 ! clk $end
$var wire 32 S read_data1 [31:0] $end
$var wire 32 T read_data2 [31:0] $end
$var wire 5 U read_reg1 [4:0] $end
$var wire 5 V read_reg2 [4:0] $end
$var wire 32 W reg_t2 [31:0] $end
$var wire 1 * reg_write $end
$var wire 32 X write_data [31:0] $end
$var wire 5 Y write_reg [4:0] $end
$upscope $end
$upscope $end
$upscope $end
$enddefinitions $end
$comment Show the parameter values. $end
$dumpall
$end
#0
$dumpvars
b1000 Y
bx X
bx W
b1000 V
b0 U
bx T
bx S
b0 R
b100 Q
b0 P
b100000000010000000000000000101 O
b1000000 N
b0 M
bx L
bx K
b0 J
b1000 I
b10 H
b0 G
b101 F
bx E
b10 D
bx C
bx B
b10 A
b0 @
bx ?
0>
bx =
0<
b11000 ;
b101 :
b101 9
b100000000010000000000000000101 8
07
b1000000000000000010100 6
b0 5
04
03
02
b1000 1
b100 0
b0 /
b0 .
bx -
bx ,
0+
0*
b0 )
b1000 (
b101 '
bx &
b1000 %
0$
0#
1"
0!
$end
#5000
b0 -
b0 C
b0 S
1!
#10000
0!
0"
#15000
b1001 %
b1001 Y
b1001000000000000101000 6
b1010 :
b1010 F
b1010 '
b1010 9
b1001 (
b1001 V
b1000 0
b1000 Q
b100000000010010000000000001010 8
b100000000010010000000000001010 O
b110000 ;
b100 /
b100 P
b100 R
1!
#20000
0!
#25000
b0 &
b0 X
1$
b0 ?
b0 E
b0 K
b0 =
b0 B
b1000 %
b1000 Y
12
1>
b1000000000000000000000 6
b0 :
b0 F
b0 '
b0 9
b1000 (
b1000 V
b101011 1
b101011 I
b1100 0
b1100 Q
b10101100000010000000000000000000 8
b10101100000010000000000000000000 O
b1100 ;
b1000 /
b1000 P
b1000 R
1!
#30000
0!
#35000
bx &
bx X
bx 5
bx M
b1010 %
b1010 Y
02
14
1*
13
b1010000000000000000000 6
b1010 (
b1010 V
b100011 1
b100011 I
b10000 0
b10000 Q
b10001100000010100000000000000000 8
b10001100000010100000000000000000 O
b10000 ;
b1100 /
b1100 P
b1100 R
1!
#40000
0!
#45000
b0x &
b0x X
b0 5
b0 M
b111 A
b111 D
b111 H
bx =
bx B
b1011 %
b1011 Y
0$
b0x ?
b0x E
b0x K
b10 @
b10 G
b10 J
04
03
0>
1+
b100001001010110000010101000 6
b101010 :
b101010 F
b101100000101010 '
b101100000101010 9
b1011 .
b1001 (
b1001 V
bx -
bx C
bx S
b1000 )
b1000 U
b0 1
b0 I
b10100 0
b10100 Q
b1000010010101100000101010 8
b1000010010101100000101010 O
b10110000010111100 ;
b10000 /
b10000 P
b10000 R
1!
#50000
0!
#55000
bx &
bx X
bx ?
bx E
bx K
b110 A
b110 D
b110 H
b0 %
b0 Y
b0 =
b0 B
b1 @
b1 G
b1 J
1<
0*
0+
b101100000000000000000000100 6
b1 :
b1 F
b1 '
b1 9
b0 .
b0 ,
b0 L
b0 T
b0 (
b0 V
b0x -
b0x C
b0x S
b1011 )
b1011 U
b100 1
b100 I
b11000 0
b11000 Q
b10001011000000000000000000001 8
b10001011000000000000000000001 O
b11100 ;
b10100 /
b10100 P
b10100 R
1!
#60000
0!
#65000
b10 A
b10 D
b10 H
b1100 %
b1100 Y
bx =
bx B
b10 @
b10 G
b10 J
0<
1*
1+
b100101010011000000010000000 6
b100000 :
b100000 F
b110000000100000 '
b110000000100000 9
b1100 .
bx ,
bx L
bx T
b1010 (
b1010 V
bx -
bx C
bx S
b1001 )
b1001 U
b0 1
b0 I
b11100 0
b11100 Q
b1001010100110000000100000 8
b1001010100110000000100000 O
b11000000010011100 ;
b11000 /
b11000 P
b11000 R
1!
#70000
0!
#75000
b110 A
b110 D
b110 H
b1111 %
b1111 Y
b100101000011110000010001000 6
b100010 :
b100010 F
b111100000100010 '
b111100000100010 9
b1111 .
b1000 (
b1000 V
b100000 0
b100000 Q
b1001010000111100000100010 8
b1001010000111100000100010 O
b11110000010101000 ;
b11100 /
b11100 P
b11100 R
1!
#80000
0!
#85000
b10 A
b10 D
b10 H
bx %
bx Y
b0 @
b0 G
b0 J
0*
0+
b0xxxxxxxxxxxxxxxxxxxxxxxxxx00 6
bx :
bx F
bx '
bx 9
bx .
bx (
bx V
bx )
bx U
bx 1
bx I
b100100 0
b100100 Q
bx 8
bx O
bx ;
b100000 /
b100000 P
b100000 R
1!
#90000
0!
#95000
b101000 0
b101000 Q
b100100 /
b100100 P
b100100 R
1!
#100000
0!
#105000
b101100 0
b101100 Q
b101000 /
b101000 P
b101000 R
1!
